odoo/addons/agreement_serviceprofile/README.rst
odoo/addons/agreement_serviceprofile/__init__.py
odoo/addons/agreement_serviceprofile/__manifest__.py
odoo/addons/agreement_serviceprofile/data/serviceprofile_stage.xml
odoo/addons/agreement_serviceprofile/i18n/agreement_serviceprofile.pot
odoo/addons/agreement_serviceprofile/i18n/de.po
odoo/addons/agreement_serviceprofile/i18n/en_US.po
odoo/addons/agreement_serviceprofile/i18n/es.po
odoo/addons/agreement_serviceprofile/i18n/es_AR.po
odoo/addons/agreement_serviceprofile/i18n/fr.po
odoo/addons/agreement_serviceprofile/i18n/it.po
odoo/addons/agreement_serviceprofile/i18n/pt.po
odoo/addons/agreement_serviceprofile/i18n/pt_BR.po
odoo/addons/agreement_serviceprofile/i18n/sv.po
odoo/addons/agreement_serviceprofile/i18n/zh_CN.po
odoo/addons/agreement_serviceprofile/models/__init__.py
odoo/addons/agreement_serviceprofile/models/agreement.py
odoo/addons/agreement_serviceprofile/models/agreement_serviceprofile.py
odoo/addons/agreement_serviceprofile/models/agreement_stage.py
odoo/addons/agreement_serviceprofile/models/product.py
odoo/addons/agreement_serviceprofile/readme/CONTRIBUTORS.md
odoo/addons/agreement_serviceprofile/readme/DESCRIPTION.md
odoo/addons/agreement_serviceprofile/security/ir.model.access.csv
odoo/addons/agreement_serviceprofile/static/description/icon.png
odoo/addons/agreement_serviceprofile/static/description/index.html
odoo/addons/agreement_serviceprofile/tests/__init__.py
odoo/addons/agreement_serviceprofile/tests/test_agreement_serviceprofile.py
odoo/addons/agreement_serviceprofile/tests/test_product.py
odoo/addons/agreement_serviceprofile/views/agreement.xml
odoo/addons/agreement_serviceprofile/views/agreement_serviceprofile.xml
odoo/addons/agreement_serviceprofile/views/product.xml
odoo_addon_agreement_serviceprofile-18.0.1.0.0.9.dist-info/METADATA
odoo_addon_agreement_serviceprofile-18.0.1.0.0.9.dist-info/WHEEL
odoo_addon_agreement_serviceprofile-18.0.1.0.0.9.dist-info/top_level.txt
odoo_addon_agreement_serviceprofile-18.0.1.0.0.9.dist-info/RECORD
